balepy/__init__.py
balepy/errors.py
balepy/client/__init__.py
balepy/client/client.py
balepy/http/__init__.py
balepy/http/api.py
balepy/methods/__init__.py
balepy/methods/messages/__init__.py
balepy/methods/messages/copy_message.py
balepy/methods/messages/delete_message.py
balepy/methods/messages/edit_message_text.py
balepy/methods/messages/forward_message.py
balepy/methods/messages/send_animation.py
balepy/methods/messages/send_audio.py
balepy/methods/messages/send_document.py
balepy/methods/messages/send_location.py
balepy/methods/messages/send_media_group.py
balepy/methods/messages/send_message.py
balepy/methods/messages/send_photo.py
balepy/methods/messages/send_video.py
balepy/methods/messages/send_voice.py
balepy/methods/updates/__init__.py
balepy/methods/updates/get_updates.py
balepy/methods/updates/get_webhook_info.py
balepy/methods/updates/set_webhook.py
balepy/methods/users/__init__.py
balepy/methods/users/get_me.py
balepy/methods/users/log_out.py
balepy/objects/__init__.py
balepy/objects/objects.py
balepy/types/__init__.py
balepy/types/results.py
balepy/types/updates.py
balepy-1.4.2.dist-info/LICENSE
balepy-1.4.2.dist-info/METADATA
balepy-1.4.2.dist-info/WHEEL
balepy-1.4.2.dist-info/top_level.txt
balepy-1.4.2.dist-info/RECORD
