Metadata-Version: 2.1
Name: balepy
Version: 1.4.2
Summary: balepy a Library Python for create bots API in bale application
Home-page: https://github.com/MamdMehrabi/balepy
Author: Mohammad, AmirAli
Author-email: mohammadmehrabi175@gmail.com
Keywords: bot,Bot,bale,robot,messangers
Classifier: Programming Language :: Python :: 3.6
Classifier: Programming Language :: Python :: 3.7
Classifier: Programming Language :: Python :: 3.8
Classifier: Programming Language :: Python :: 3.9
Classifier: Programming Language :: Python :: 3.10
Classifier: Programming Language :: Python :: 3.11
Classifier: Programming Language :: Python :: 3.12
Classifier: License :: OSI Approved :: MIT License
Requires-Python: ~=3.6
License-File: LICENSE
Requires-Dist: aiohttp
